{
  "oi_history": [
    {
      "timestamp": 1768753800,
      "value": 46520861
    },
    {
      "timestamp": 1768754700,
      "value": 46524014
    },
    {
      "timestamp": 1768755600,
      "value": 46399303
    },
    {
      "timestamp": 1768756500,
      "value": 46405313
    },
    {
      "timestamp": 1768757400,
      "value": 46304348
    },
    {
      "timestamp": 1768758300,
      "value": 46315575
    },
    {
      "timestamp": 1768759200,
      "value": 46269611
    },
    {
      "timestamp": 1768760100,
      "value": 46204616
    },
    {
      "timestamp": 1768761000,
      "value": 46139576
    },
    {
      "timestamp": 1768761900,
      "value": 46178340
    },
    {
      "timestamp": 1768762800,
      "value": 46261113
    },
    {
      "timestamp": 1768763700,
      "value": 46245544
    },
    {
      "timestamp": 1768764600,
      "value": 46251965
    },
    {
      "timestamp": 1768765500,
      "value": 46211965
    },
    {
      "timestamp": 1768766400,
      "value": 46263074
    },
    {
      "timestamp": 1768767300,
      "value": 46184374
    },
    {
      "timestamp": 1768768200,
      "value": 46129937
    },
    {
      "timestamp": 1768769100,
      "value": 46166963
    },
    {
      "timestamp": 1768770000,
      "value": 46126746
    },
    {
      "timestamp": 1768770900,
      "value": 46058510
    },
    {
      "timestamp": 1768771800,
      "value": 46028197
    },
    {
      "timestamp": 1768772700,
      "value": 46146637
    },
    {
      "timestamp": 1768773600,
      "value": 46073737
    },
    {
      "timestamp": 1768774500,
      "value": 46064350
    },
    {
      "timestamp": 1768775400,
      "value": 46044174
    },
    {
      "timestamp": 1768776300,
      "value": 45999899
    },
    {
      "timestamp": 1768777200,
      "value": 45954601
    },
    {
      "timestamp": 1768778100,
      "value": 45983814
    },
    {
      "timestamp": 1768779000,
      "value": 45946203
    },
    {
      "timestamp": 1768779900,
      "value": 45775973
    },
    {
      "timestamp": 1768780800,
      "value": 44435628
    },
    {
      "timestamp": 1768781700,
      "value": 44692778
    },
    {
      "timestamp": 1768782600,
      "value": 45177302
    },
    {
      "timestamp": 1768783500,
      "value": 45753395
    },
    {
      "timestamp": 1768784400,
      "value": 45789591
    },
    {
      "timestamp": 1768785300,
      "value": 45794728
    },
    {
      "timestamp": 1768786200,
      "value": 45810361
    },
    {
      "timestamp": 1768787100,
      "value": 45814708
    },
    {
      "timestamp": 1768788000,
      "value": 45823901
    },
    {
      "timestamp": 1768788900,
      "value": 45698684
    },
    {
      "timestamp": 1768789800,
      "value": 45603753
    },
    {
      "timestamp": 1768790700,
      "value": 45500678
    },
    {
      "timestamp": 1768791600,
      "value": 45327470
    },
    {
      "timestamp": 1768792500,
      "value": 45336785
    },
    {
      "timestamp": 1768793400,
      "value": 45477228
    },
    {
      "timestamp": 1768794300,
      "value": 45475063
    },
    {
      "timestamp": 1768795200,
      "value": 45359670
    },
    {
      "timestamp": 1768796100,
      "value": 45365064
    },
    {
      "timestamp": 1768797000,
      "value": 45379661
    },
    {
      "timestamp": 1768797900,
      "value": 45388181
    },
    {
      "timestamp": 1768798800,
      "value": 45250212
    },
    {
      "timestamp": 1768799700,
      "value": 45267999
    },
    {
      "timestamp": 1768800600,
      "value": 45505065
    },
    {
      "timestamp": 1768801500,
      "value": 45462540
    },
    {
      "timestamp": 1768802400,
      "value": 45471655
    },
    {
      "timestamp": 1768803300,
      "value": 45433204
    },
    {
      "timestamp": 1768804200,
      "value": 45327591
    },
    {
      "timestamp": 1768805100,
      "value": 45267716
    },
    {
      "timestamp": 1768806000,
      "value": 45222407
    },
    {
      "timestamp": 1768806900,
      "value": 45139652
    },
    {
      "timestamp": 1768807800,
      "value": 44980689
    },
    {
      "timestamp": 1768808700,
      "value": 44894337
    },
    {
      "timestamp": 1768809600,
      "value": 44739558
    },
    {
      "timestamp": 1768810500,
      "value": 44502423
    },
    {
      "timestamp": 1768811400,
      "value": 44409809
    },
    {
      "timestamp": 1768812300,
      "value": 44438504
    },
    {
      "timestamp": 1768813200,
      "value": 44366982
    },
    {
      "timestamp": 1768814100,
      "value": 44316660
    },
    {
      "timestamp": 1768815000,
      "value": 44183212
    },
    {
      "timestamp": 1768815900,
      "value": 44097128
    },
    {
      "timestamp": 1768816800,
      "value": 43910295
    },
    {
      "timestamp": 1768817700,
      "value": 43898224
    },
    {
      "timestamp": 1768818600,
      "value": 43833808
    },
    {
      "timestamp": 1768819500,
      "value": 43781368
    },
    {
      "timestamp": 1768820400,
      "value": 43726468
    },
    {
      "timestamp": 1768821300,
      "value": 43533899
    },
    {
      "timestamp": 1768822200,
      "value": 43696488
    },
    {
      "timestamp": 1768823100,
      "value": 44126329
    },
    {
      "timestamp": 1768824000,
      "value": 44478950
    },
    {
      "timestamp": 1768824900,
      "value": 46541051
    },
    {
      "timestamp": 1768825800,
      "value": 47685758
    },
    {
      "timestamp": 1768826700,
      "value": 47256121
    },
    {
      "timestamp": 1768827600,
      "value": 46788708
    },
    {
      "timestamp": 1768828500,
      "value": 46180143
    },
    {
      "timestamp": 1768829400,
      "value": 45409718
    },
    {
      "timestamp": 1768830300,
      "value": 45178644
    },
    {
      "timestamp": 1768831200,
      "value": 44960453
    },
    {
      "timestamp": 1768832100,
      "value": 44702398
    },
    {
      "timestamp": 1768833000,
      "value": 44631596
    },
    {
      "timestamp": 1768833900,
      "value": 44600459
    },
    {
      "timestamp": 1768834800,
      "value": 44586274
    },
    {
      "timestamp": 1768835700,
      "value": 44519891
    },
    {
      "timestamp": 1768836600,
      "value": 44311464
    },
    {
      "timestamp": 1768837500,
      "value": 44219936
    },
    {
      "timestamp": 1768838400,
      "value": 43627593
    },
    {
      "timestamp": 1768839300,
      "value": 43396095
    },
    {
      "timestamp": 1768840200,
      "value": 43063124
    }
  ],
  "funding_rate": null,
  "ls_ratio": 0.6315875346712352,
  "liquidations": {
    "longs": 32403,
    "shorts": 0
  },
  "oi_status": "aggregated",
  "coinalyze_symbol": "AVNTUSDT_PERP.A",
  "fetched_at": 1768840663706
}