{
  "oi_history": [
    {
      "timestamp": 1768685400,
      "value": 58555825
    },
    {
      "timestamp": 1768686300,
      "value": 58518564
    },
    {
      "timestamp": 1768687200,
      "value": 58511810
    },
    {
      "timestamp": 1768688100,
      "value": 58490523
    },
    {
      "timestamp": 1768689000,
      "value": 58471357
    },
    {
      "timestamp": 1768689900,
      "value": 58431312
    },
    {
      "timestamp": 1768690800,
      "value": 58400896
    },
    {
      "timestamp": 1768691700,
      "value": 58384984
    },
    {
      "timestamp": 1768692600,
      "value": 58349093
    },
    {
      "timestamp": 1768693500,
      "value": 58300866
    },
    {
      "timestamp": 1768694400,
      "value": 58297398
    },
    {
      "timestamp": 1768695300,
      "value": 58331175
    },
    {
      "timestamp": 1768696200,
      "value": 58300371
    },
    {
      "timestamp": 1768697100,
      "value": 58266219
    },
    {
      "timestamp": 1768698000,
      "value": 58217547
    },
    {
      "timestamp": 1768698900,
      "value": 58417523
    },
    {
      "timestamp": 1768699800,
      "value": 58420963
    },
    {
      "timestamp": 1768700700,
      "value": 58554683
    },
    {
      "timestamp": 1768701600,
      "value": 58559399
    },
    {
      "timestamp": 1768702500,
      "value": 58496385
    },
    {
      "timestamp": 1768703400,
      "value": 58563126
    },
    {
      "timestamp": 1768704300,
      "value": 58564788
    },
    {
      "timestamp": 1768705200,
      "value": 58533143
    },
    {
      "timestamp": 1768706100,
      "value": 58554763
    },
    {
      "timestamp": 1768707000,
      "value": 58591567
    },
    {
      "timestamp": 1768707900,
      "value": 58639797
    },
    {
      "timestamp": 1768708800,
      "value": 58708323
    },
    {
      "timestamp": 1768709700,
      "value": 58699338
    },
    {
      "timestamp": 1768710600,
      "value": 59064798
    },
    {
      "timestamp": 1768711500,
      "value": 59078844
    },
    {
      "timestamp": 1768712400,
      "value": 59007159
    },
    {
      "timestamp": 1768713300,
      "value": 59008684
    },
    {
      "timestamp": 1768714200,
      "value": 59027291
    },
    {
      "timestamp": 1768715100,
      "value": 59073664
    },
    {
      "timestamp": 1768716000,
      "value": 59036016
    },
    {
      "timestamp": 1768716900,
      "value": 59028407
    },
    {
      "timestamp": 1768717800,
      "value": 59015180
    },
    {
      "timestamp": 1768718700,
      "value": 58969870
    },
    {
      "timestamp": 1768719600,
      "value": 58901430
    },
    {
      "timestamp": 1768720500,
      "value": 58911314
    },
    {
      "timestamp": 1768721400,
      "value": 58771010
    },
    {
      "timestamp": 1768722300,
      "value": 58745872
    },
    {
      "timestamp": 1768723200,
      "value": 58662319
    },
    {
      "timestamp": 1768724100,
      "value": 58737840
    },
    {
      "timestamp": 1768725000,
      "value": 58675691
    },
    {
      "timestamp": 1768725900,
      "value": 58686173
    },
    {
      "timestamp": 1768726800,
      "value": 58660904
    },
    {
      "timestamp": 1768727700,
      "value": 58660127
    },
    {
      "timestamp": 1768728600,
      "value": 58652932
    },
    {
      "timestamp": 1768729500,
      "value": 58848893
    },
    {
      "timestamp": 1768730400,
      "value": 58870211
    },
    {
      "timestamp": 1768731300,
      "value": 58820081
    },
    {
      "timestamp": 1768732200,
      "value": 58841016
    },
    {
      "timestamp": 1768733100,
      "value": 58846285
    },
    {
      "timestamp": 1768734000,
      "value": 58812842
    },
    {
      "timestamp": 1768734900,
      "value": 58786370
    },
    {
      "timestamp": 1768735800,
      "value": 58786046
    },
    {
      "timestamp": 1768736700,
      "value": 58758769
    },
    {
      "timestamp": 1768737600,
      "value": 58794605
    },
    {
      "timestamp": 1768738500,
      "value": 58821245
    },
    {
      "timestamp": 1768739400,
      "value": 58828031
    },
    {
      "timestamp": 1768740300,
      "value": 58872307
    },
    {
      "timestamp": 1768741200,
      "value": 58810253
    },
    {
      "timestamp": 1768742100,
      "value": 58698099
    },
    {
      "timestamp": 1768743000,
      "value": 58611319
    },
    {
      "timestamp": 1768743900,
      "value": 58648575
    },
    {
      "timestamp": 1768744800,
      "value": 58663658
    },
    {
      "timestamp": 1768745700,
      "value": 58809443
    },
    {
      "timestamp": 1768746600,
      "value": 58761470
    },
    {
      "timestamp": 1768747500,
      "value": 58800510
    },
    {
      "timestamp": 1768748400,
      "value": 58695328
    },
    {
      "timestamp": 1768749300,
      "value": 58739311
    },
    {
      "timestamp": 1768750200,
      "value": 58730003
    },
    {
      "timestamp": 1768751100,
      "value": 58646574
    },
    {
      "timestamp": 1768752000,
      "value": 58635543
    },
    {
      "timestamp": 1768752900,
      "value": 58666637
    },
    {
      "timestamp": 1768753800,
      "value": 58636491
    },
    {
      "timestamp": 1768754700,
      "value": 58541304
    },
    {
      "timestamp": 1768755600,
      "value": 58508924
    },
    {
      "timestamp": 1768756500,
      "value": 58525226
    },
    {
      "timestamp": 1768757400,
      "value": 58499274
    },
    {
      "timestamp": 1768758300,
      "value": 58524667
    },
    {
      "timestamp": 1768759200,
      "value": 58567567
    },
    {
      "timestamp": 1768760100,
      "value": 58553828
    },
    {
      "timestamp": 1768761000,
      "value": 58590838
    },
    {
      "timestamp": 1768761900,
      "value": 58580516
    },
    {
      "timestamp": 1768762800,
      "value": 58518844
    },
    {
      "timestamp": 1768763700,
      "value": 58531289
    },
    {
      "timestamp": 1768764600,
      "value": 58559233
    },
    {
      "timestamp": 1768765500,
      "value": 58581305
    },
    {
      "timestamp": 1768766400,
      "value": 58551413
    },
    {
      "timestamp": 1768767300,
      "value": 58561166
    },
    {
      "timestamp": 1768768200,
      "value": 58561958
    },
    {
      "timestamp": 1768769100,
      "value": 58570358
    },
    {
      "timestamp": 1768770000,
      "value": 58548234
    },
    {
      "timestamp": 1768770900,
      "value": 58541286
    },
    {
      "timestamp": 1768771800,
      "value": 58533501
    }
  ],
  "funding_rate": null,
  "ls_ratio": 1.4551927326295115,
  "liquidations": {
    "longs": 3916,
    "shorts": 51
  },
  "oi_status": "aggregated",
  "coinalyze_symbol": "JUPUSDT_PERP.A",
  "fetched_at": 1768772013383
}