{
  "oi_history": [
    {
      "timestamp": 1768682700,
      "value": 1962450.3
    },
    {
      "timestamp": 1768683600,
      "value": 1962737.9
    },
    {
      "timestamp": 1768684500,
      "value": 1962758.9
    },
    {
      "timestamp": 1768685400,
      "value": 1963405.3
    },
    {
      "timestamp": 1768686300,
      "value": 1962721.5
    },
    {
      "timestamp": 1768687200,
      "value": 1962897.6
    },
    {
      "timestamp": 1768688100,
      "value": 1962332.1
    },
    {
      "timestamp": 1768689000,
      "value": 1964607.7
    },
    {
      "timestamp": 1768689900,
      "value": 1965080.8
    },
    {
      "timestamp": 1768690800,
      "value": 1965066.8
    },
    {
      "timestamp": 1768691700,
      "value": 1962878.2
    },
    {
      "timestamp": 1768692600,
      "value": 1962206.7
    },
    {
      "timestamp": 1768693500,
      "value": 1962226.2
    },
    {
      "timestamp": 1768694400,
      "value": 1956152.2
    },
    {
      "timestamp": 1768695300,
      "value": 1954859.7
    },
    {
      "timestamp": 1768696200,
      "value": 1954912.2
    },
    {
      "timestamp": 1768697100,
      "value": 1954866.5
    },
    {
      "timestamp": 1768698000,
      "value": 1954989.6
    },
    {
      "timestamp": 1768698900,
      "value": 1954751.9
    },
    {
      "timestamp": 1768699800,
      "value": 1955371.8
    },
    {
      "timestamp": 1768700700,
      "value": 1955007
    },
    {
      "timestamp": 1768701600,
      "value": 1955844.3
    },
    {
      "timestamp": 1768702500,
      "value": 1956264.5
    },
    {
      "timestamp": 1768703400,
      "value": 1959135.4
    },
    {
      "timestamp": 1768704300,
      "value": 1959125.2
    },
    {
      "timestamp": 1768705200,
      "value": 1959560.1
    },
    {
      "timestamp": 1768706100,
      "value": 1959212.1
    },
    {
      "timestamp": 1768707000,
      "value": 1959147.8
    },
    {
      "timestamp": 1768707900,
      "value": 1958958.8
    },
    {
      "timestamp": 1768708800,
      "value": 1961538.6
    },
    {
      "timestamp": 1768709700,
      "value": 1962459.2
    },
    {
      "timestamp": 1768710600,
      "value": 1960711.3
    },
    {
      "timestamp": 1768711500,
      "value": 1959724.8
    },
    {
      "timestamp": 1768712400,
      "value": 1959996.8
    },
    {
      "timestamp": 1768713300,
      "value": 1959728
    },
    {
      "timestamp": 1768714200,
      "value": 1959560.3
    },
    {
      "timestamp": 1768715100,
      "value": 1958952.9
    },
    {
      "timestamp": 1768716000,
      "value": 1960235.3
    },
    {
      "timestamp": 1768716900,
      "value": 1960009.3
    },
    {
      "timestamp": 1768717800,
      "value": 1959621.6
    },
    {
      "timestamp": 1768718700,
      "value": 1959747.3
    },
    {
      "timestamp": 1768719600,
      "value": 1961024
    },
    {
      "timestamp": 1768720500,
      "value": 1961100
    },
    {
      "timestamp": 1768721400,
      "value": 1962028.4
    },
    {
      "timestamp": 1768722300,
      "value": 1962569.5
    },
    {
      "timestamp": 1768723200,
      "value": 1962737.5
    },
    {
      "timestamp": 1768724100,
      "value": 1962092.5
    },
    {
      "timestamp": 1768725000,
      "value": 1960902.5
    },
    {
      "timestamp": 1768725900,
      "value": 1960928.4
    },
    {
      "timestamp": 1768726800,
      "value": 1961302
    },
    {
      "timestamp": 1768727700,
      "value": 1960385.6
    },
    {
      "timestamp": 1768728600,
      "value": 1960170
    },
    {
      "timestamp": 1768729500,
      "value": 1959572.4
    },
    {
      "timestamp": 1768730400,
      "value": 1960569.1
    },
    {
      "timestamp": 1768731300,
      "value": 1962680.6
    },
    {
      "timestamp": 1768732200,
      "value": 1961821.4
    },
    {
      "timestamp": 1768733100,
      "value": 1961685.9
    },
    {
      "timestamp": 1768734000,
      "value": 1961813
    },
    {
      "timestamp": 1768734900,
      "value": 1962494.7
    },
    {
      "timestamp": 1768735800,
      "value": 1960485.1
    },
    {
      "timestamp": 1768736700,
      "value": 1964984.1
    },
    {
      "timestamp": 1768737600,
      "value": 1960698.6
    },
    {
      "timestamp": 1768738500,
      "value": 1956515.2
    },
    {
      "timestamp": 1768739400,
      "value": 1958854.2
    },
    {
      "timestamp": 1768740300,
      "value": 1958295.6
    },
    {
      "timestamp": 1768741200,
      "value": 1959475.1
    },
    {
      "timestamp": 1768742100,
      "value": 1957607.2
    },
    {
      "timestamp": 1768743000,
      "value": 1956389.5
    },
    {
      "timestamp": 1768743900,
      "value": 1956060.4
    },
    {
      "timestamp": 1768744800,
      "value": 1953595.2
    },
    {
      "timestamp": 1768745700,
      "value": 1951384.3
    },
    {
      "timestamp": 1768746600,
      "value": 1951346.6
    },
    {
      "timestamp": 1768747500,
      "value": 1950489.4
    },
    {
      "timestamp": 1768748400,
      "value": 1949195
    },
    {
      "timestamp": 1768749300,
      "value": 1948219.1
    },
    {
      "timestamp": 1768750200,
      "value": 1948970.8
    },
    {
      "timestamp": 1768751100,
      "value": 1948971.9
    },
    {
      "timestamp": 1768752000,
      "value": 1944790.6
    },
    {
      "timestamp": 1768752900,
      "value": 1946858.8
    },
    {
      "timestamp": 1768753800,
      "value": 1946277.5
    },
    {
      "timestamp": 1768754700,
      "value": 1946473.3
    },
    {
      "timestamp": 1768755600,
      "value": 1946731.9
    },
    {
      "timestamp": 1768756500,
      "value": 1946758.2
    },
    {
      "timestamp": 1768757400,
      "value": 1945468.2
    },
    {
      "timestamp": 1768758300,
      "value": 1946818.9
    },
    {
      "timestamp": 1768759200,
      "value": 1941456.7
    },
    {
      "timestamp": 1768760100,
      "value": 1935424.2
    },
    {
      "timestamp": 1768761000,
      "value": 1936508.6
    },
    {
      "timestamp": 1768761900,
      "value": 1936834
    },
    {
      "timestamp": 1768762800,
      "value": 1935831.4
    },
    {
      "timestamp": 1768763700,
      "value": 1933919.8
    },
    {
      "timestamp": 1768764600,
      "value": 1924153.5
    },
    {
      "timestamp": 1768765500,
      "value": 1923681.8
    },
    {
      "timestamp": 1768766400,
      "value": 1924213.3
    },
    {
      "timestamp": 1768767300,
      "value": 1924062
    },
    {
      "timestamp": 1768768200,
      "value": 1924197.5
    },
    {
      "timestamp": 1768769100,
      "value": 1924187.8
    }
  ],
  "funding_rate": null,
  "ls_ratio": 1.4348672997321645,
  "liquidations": {
    "longs": 96.49999999999999,
    "shorts": 0
  },
  "oi_status": "aggregated",
  "coinalyze_symbol": "OGUSDT_PERP.A",
  "fetched_at": 1768769554678
}