[
  {
    "time": 1768590900000,
    "open": 0.30773,
    "high": 0.30835,
    "low": 0.30771,
    "close": 0.30835,
    "volume": 77
  },
  {
    "time": 1768591800000,
    "open": 0.30837,
    "high": 0.30849,
    "low": 0.30833,
    "close": 0.30844,
    "volume": 121
  },
  {
    "time": 1768592700000,
    "open": 0.30847,
    "high": 0.30881,
    "low": 0.30847,
    "close": 0.3086,
    "volume": 125
  },
  {
    "time": 1768593600000,
    "open": 0.30848,
    "high": 0.30908,
    "low": 0.30848,
    "close": 0.30908,
    "volume": 719
  },
  {
    "time": 1768594500000,
    "open": 0.30908,
    "high": 0.30968,
    "low": 0.30908,
    "close": 0.30954,
    "volume": 270
  },
  {
    "time": 1768595400000,
    "open": 0.30934,
    "high": 0.30977,
    "low": 0.30886,
    "close": 0.30976,
    "volume": 239
  },
  {
    "time": 1768596300000,
    "open": 0.3098,
    "high": 0.31064,
    "low": 0.3098,
    "close": 0.31034,
    "volume": 531
  },
  {
    "time": 1768597200000,
    "open": 0.31047,
    "high": 0.31074,
    "low": 0.31033,
    "close": 0.31071,
    "volume": 282
  },
  {
    "time": 1768598100000,
    "open": 0.31062,
    "high": 0.31091,
    "low": 0.31037,
    "close": 0.3107,
    "volume": 199
  },
  {
    "time": 1768599000000,
    "open": 0.31074,
    "high": 0.31085,
    "low": 0.3102,
    "close": 0.31024,
    "volume": 248
  },
  {
    "time": 1768599900000,
    "open": 0.31025,
    "high": 0.3107,
    "low": 0.31025,
    "close": 0.31054,
    "volume": 191
  },
  {
    "time": 1768600800000,
    "open": 0.31057,
    "high": 0.31077,
    "low": 0.31037,
    "close": 0.31054,
    "volume": 409
  },
  {
    "time": 1768601700000,
    "open": 0.31067,
    "high": 0.31088,
    "low": 0.31048,
    "close": 0.31079,
    "volume": 216
  },
  {
    "time": 1768602600000,
    "open": 0.31086,
    "high": 0.31106,
    "low": 0.31083,
    "close": 0.31101,
    "volume": 351
  },
  {
    "time": 1768603500000,
    "open": 0.3111,
    "high": 0.31117,
    "low": 0.31086,
    "close": 0.31103,
    "volume": 368
  },
  {
    "time": 1768604400000,
    "open": 0.31103,
    "high": 0.31103,
    "low": 0.3107,
    "close": 0.31098,
    "volume": 360
  },
  {
    "time": 1768605300000,
    "open": 0.31094,
    "high": 0.31097,
    "low": 0.31026,
    "close": 0.3103,
    "volume": 258
  },
  {
    "time": 1768606200000,
    "open": 0.31028,
    "high": 0.31032,
    "low": 0.3093,
    "close": 0.30934,
    "volume": 606
  },
  {
    "time": 1768607100000,
    "open": 0.3093,
    "high": 0.30967,
    "low": 0.30901,
    "close": 0.30958,
    "volume": 240
  },
  {
    "time": 1768608000000,
    "open": 0.30964,
    "high": 0.3098,
    "low": 0.3089,
    "close": 0.30898,
    "volume": 248
  },
  {
    "time": 1768608900000,
    "open": 0.30901,
    "high": 0.30944,
    "low": 0.30898,
    "close": 0.30934,
    "volume": 148
  },
  {
    "time": 1768609800000,
    "open": 0.30927,
    "high": 0.3098,
    "low": 0.30925,
    "close": 0.30962,
    "volume": 209
  },
  {
    "time": 1768610700000,
    "open": 0.30973,
    "high": 0.30984,
    "low": 0.30973,
    "close": 0.30981,
    "volume": 30
  },
  {
    "time": 1768611600000,
    "open": 0.30984,
    "high": 0.31016,
    "low": 0.30984,
    "close": 0.31005,
    "volume": 111
  },
  {
    "time": 1768612500000,
    "open": 0.3101,
    "high": 0.31066,
    "low": 0.3101,
    "close": 0.31028,
    "volume": 190
  },
  {
    "time": 1768613400000,
    "open": 0.31027,
    "high": 0.31027,
    "low": 0.30946,
    "close": 0.30959,
    "volume": 232
  },
  {
    "time": 1768614300000,
    "open": 0.30963,
    "high": 0.30986,
    "low": 0.30959,
    "close": 0.30983,
    "volume": 133
  },
  {
    "time": 1768615200000,
    "open": 0.30976,
    "high": 0.30996,
    "low": 0.3096,
    "close": 0.3096,
    "volume": 214
  },
  {
    "time": 1768616100000,
    "open": 0.30965,
    "high": 0.30994,
    "low": 0.3096,
    "close": 0.30967,
    "volume": 128
  },
  {
    "time": 1768617000000,
    "open": 0.30969,
    "high": 0.30997,
    "low": 0.30956,
    "close": 0.30996,
    "volume": 133
  },
  {
    "time": 1768617900000,
    "open": 0.31,
    "high": 0.3105,
    "low": 0.30991,
    "close": 0.31043,
    "volume": 113
  },
  {
    "time": 1768618800000,
    "open": 0.31044,
    "high": 0.31085,
    "low": 0.31033,
    "close": 0.31066,
    "volume": 987
  },
  {
    "time": 1768619700000,
    "open": 0.31065,
    "high": 0.31082,
    "low": 0.31037,
    "close": 0.31037,
    "volume": 1396
  },
  {
    "time": 1768620600000,
    "open": 0.31034,
    "high": 0.31063,
    "low": 0.31024,
    "close": 0.31062,
    "volume": 64
  },
  {
    "time": 1768621500000,
    "open": 0.31061,
    "high": 0.31061,
    "low": 0.31032,
    "close": 0.31045,
    "volume": 69
  },
  {
    "time": 1768622400000,
    "open": 0.31057,
    "high": 0.31057,
    "low": 0.30988,
    "close": 0.3105,
    "volume": 405
  },
  {
    "time": 1768623300000,
    "open": 0.31051,
    "high": 0.31151,
    "low": 0.31051,
    "close": 0.31151,
    "volume": 158
  },
  {
    "time": 1768624200000,
    "open": 0.31143,
    "high": 0.31158,
    "low": 0.31142,
    "close": 0.31157,
    "volume": 111
  },
  {
    "time": 1768625100000,
    "open": 0.31156,
    "high": 0.31196,
    "low": 0.31156,
    "close": 0.31187,
    "volume": 104
  },
  {
    "time": 1768626000000,
    "open": 0.31195,
    "high": 0.31222,
    "low": 0.31182,
    "close": 0.31185,
    "volume": 322
  },
  {
    "time": 1768626900000,
    "open": 0.31188,
    "high": 0.31188,
    "low": 0.31135,
    "close": 0.31141,
    "volume": 567
  },
  {
    "time": 1768627800000,
    "open": 0.31145,
    "high": 0.3115,
    "low": 0.31111,
    "close": 0.31111,
    "volume": 106
  },
  {
    "time": 1768628700000,
    "open": 0.31108,
    "high": 0.31137,
    "low": 0.31108,
    "close": 0.31135,
    "volume": 130
  },
  {
    "time": 1768629600000,
    "open": 0.31132,
    "high": 0.31163,
    "low": 0.31131,
    "close": 0.31149,
    "volume": 293
  },
  {
    "time": 1768630500000,
    "open": 0.3115,
    "high": 0.31214,
    "low": 0.3115,
    "close": 0.31187,
    "volume": 166
  },
  {
    "time": 1768631400000,
    "open": 0.31195,
    "high": 0.31205,
    "low": 0.31176,
    "close": 0.31184,
    "volume": 136
  },
  {
    "time": 1768632300000,
    "open": 0.31184,
    "high": 0.31184,
    "low": 0.31105,
    "close": 0.31182,
    "volume": 369
  },
  {
    "time": 1768633200000,
    "open": 0.31177,
    "high": 0.31185,
    "low": 0.31162,
    "close": 0.31185,
    "volume": 79
  },
  {
    "time": 1768634100000,
    "open": 0.31194,
    "high": 0.31199,
    "low": 0.31126,
    "close": 0.31135,
    "volume": 202
  },
  {
    "time": 1768635000000,
    "open": 0.31135,
    "high": 0.31159,
    "low": 0.31089,
    "close": 0.31157,
    "volume": 252
  },
  {
    "time": 1768635900000,
    "open": 0.31159,
    "high": 0.31187,
    "low": 0.31139,
    "close": 0.31177,
    "volume": 197
  },
  {
    "time": 1768636800000,
    "open": 0.31176,
    "high": 0.31199,
    "low": 0.31165,
    "close": 0.31174,
    "volume": 163
  },
  {
    "time": 1768637700000,
    "open": 0.31168,
    "high": 0.31168,
    "low": 0.31041,
    "close": 0.31067,
    "volume": 344
  },
  {
    "time": 1768638600000,
    "open": 0.31063,
    "high": 0.31064,
    "low": 0.30944,
    "close": 0.30944,
    "volume": 429
  },
  {
    "time": 1768639500000,
    "open": 0.30949,
    "high": 0.30972,
    "low": 0.30926,
    "close": 0.30953,
    "volume": 217
  },
  {
    "time": 1768640400000,
    "open": 0.30954,
    "high": 0.31019,
    "low": 0.3094,
    "close": 0.31005,
    "volume": 626
  },
  {
    "time": 1768641300000,
    "open": 0.31014,
    "high": 0.31028,
    "low": 0.31004,
    "close": 0.31027,
    "volume": 76
  },
  {
    "time": 1768642200000,
    "open": 0.31018,
    "high": 0.31043,
    "low": 0.31018,
    "close": 0.31034,
    "volume": 49
  },
  {
    "time": 1768643100000,
    "open": 0.31018,
    "high": 0.31213,
    "low": 0.31018,
    "close": 0.31124,
    "volume": 2762
  },
  {
    "time": 1768644000000,
    "open": 0.31124,
    "high": 0.31144,
    "low": 0.31108,
    "close": 0.31144,
    "volume": 182
  },
  {
    "time": 1768644900000,
    "open": 0.31155,
    "high": 0.31195,
    "low": 0.31151,
    "close": 0.31191,
    "volume": 380
  },
  {
    "time": 1768645800000,
    "open": 0.31191,
    "high": 0.31239,
    "low": 0.31188,
    "close": 0.31203,
    "volume": 404
  },
  {
    "time": 1768646700000,
    "open": 0.31203,
    "high": 0.31232,
    "low": 0.31177,
    "close": 0.31227,
    "volume": 408
  },
  {
    "time": 1768647600000,
    "open": 0.31213,
    "high": 0.31225,
    "low": 0.31184,
    "close": 0.31214,
    "volume": 176
  },
  {
    "time": 1768648500000,
    "open": 0.31215,
    "high": 0.31295,
    "low": 0.31215,
    "close": 0.31285,
    "volume": 520
  },
  {
    "time": 1768649400000,
    "open": 0.31291,
    "high": 0.31327,
    "low": 0.31263,
    "close": 0.3128,
    "volume": 546
  },
  {
    "time": 1768650300000,
    "open": 0.31273,
    "high": 0.31352,
    "low": 0.31263,
    "close": 0.31279,
    "volume": 323
  },
  {
    "time": 1768651200000,
    "open": 0.31278,
    "high": 0.31337,
    "low": 0.31277,
    "close": 0.313,
    "volume": 202
  },
  {
    "time": 1768652100000,
    "open": 0.31297,
    "high": 0.31328,
    "low": 0.31219,
    "close": 0.31223,
    "volume": 227
  },
  {
    "time": 1768653000000,
    "open": 0.31228,
    "high": 0.31285,
    "low": 0.31185,
    "close": 0.31251,
    "volume": 242
  },
  {
    "time": 1768653900000,
    "open": 0.31251,
    "high": 0.31291,
    "low": 0.31243,
    "close": 0.31258,
    "volume": 171
  },
  {
    "time": 1768654800000,
    "open": 0.31259,
    "high": 0.31274,
    "low": 0.31222,
    "close": 0.31255,
    "volume": 272
  },
  {
    "time": 1768655700000,
    "open": 0.31249,
    "high": 0.31299,
    "low": 0.31249,
    "close": 0.31295,
    "volume": 198
  },
  {
    "time": 1768656600000,
    "open": 0.31299,
    "high": 0.31322,
    "low": 0.31299,
    "close": 0.31322,
    "volume": 138
  },
  {
    "time": 1768657500000,
    "open": 0.31321,
    "high": 0.31384,
    "low": 0.31321,
    "close": 0.31368,
    "volume": 248
  },
  {
    "time": 1768658400000,
    "open": 0.31371,
    "high": 0.31486,
    "low": 0.3137,
    "close": 0.31478,
    "volume": 730
  },
  {
    "time": 1768659300000,
    "open": 0.31485,
    "high": 0.31494,
    "low": 0.31387,
    "close": 0.31428,
    "volume": 857
  },
  {
    "time": 1768660200000,
    "open": 0.31428,
    "high": 0.31442,
    "low": 0.31386,
    "close": 0.31413,
    "volume": 354
  },
  {
    "time": 1768661100000,
    "open": 0.31414,
    "high": 0.31432,
    "low": 0.31414,
    "close": 0.31416,
    "volume": 137
  },
  {
    "time": 1768662000000,
    "open": 0.31421,
    "high": 0.3146,
    "low": 0.31421,
    "close": 0.3146,
    "volume": 165
  },
  {
    "time": 1768662900000,
    "open": 0.31471,
    "high": 0.315,
    "low": 0.31436,
    "close": 0.315,
    "volume": 1218
  },
  {
    "time": 1768663800000,
    "open": 0.31498,
    "high": 0.31563,
    "low": 0.31498,
    "close": 0.3154,
    "volume": 1154
  },
  {
    "time": 1768664700000,
    "open": 0.31545,
    "high": 0.31557,
    "low": 0.31438,
    "close": 0.31474,
    "volume": 597
  },
  {
    "time": 1768665600000,
    "open": 0.31481,
    "high": 0.31612,
    "low": 0.31481,
    "close": 0.31589,
    "volume": 680
  },
  {
    "time": 1768666500000,
    "open": 0.31579,
    "high": 0.31579,
    "low": 0.31455,
    "close": 0.31513,
    "volume": 717
  },
  {
    "time": 1768667400000,
    "open": 0.3152,
    "high": 0.31528,
    "low": 0.31485,
    "close": 0.31512,
    "volume": 480
  },
  {
    "time": 1768668300000,
    "open": 0.31503,
    "high": 0.31513,
    "low": 0.31468,
    "close": 0.3151,
    "volume": 318
  },
  {
    "time": 1768669200000,
    "open": 0.31514,
    "high": 0.31522,
    "low": 0.31476,
    "close": 0.3148,
    "volume": 240
  },
  {
    "time": 1768670100000,
    "open": 0.31474,
    "high": 0.31528,
    "low": 0.31474,
    "close": 0.31526,
    "volume": 340
  },
  {
    "time": 1768671000000,
    "open": 0.31521,
    "high": 0.31596,
    "low": 0.3152,
    "close": 0.31578,
    "volume": 601
  },
  {
    "time": 1768671900000,
    "open": 0.31577,
    "high": 0.31618,
    "low": 0.31569,
    "close": 0.31607,
    "volume": 591
  },
  {
    "time": 1768672800000,
    "open": 0.316,
    "high": 0.31619,
    "low": 0.31575,
    "close": 0.31619,
    "volume": 445
  },
  {
    "time": 1768673700000,
    "open": 0.31617,
    "high": 0.31655,
    "low": 0.31588,
    "close": 0.31655,
    "volume": 417
  },
  {
    "time": 1768674600000,
    "open": 0.31656,
    "high": 0.3168,
    "low": 0.31588,
    "close": 0.31606,
    "volume": 377
  },
  {
    "time": 1768675500000,
    "open": 0.31596,
    "high": 0.3162,
    "low": 0.31591,
    "close": 0.31591,
    "volume": 265
  },
  {
    "time": 1768676400000,
    "open": 0.31588,
    "high": 0.31614,
    "low": 0.31582,
    "close": 0.31604,
    "volume": 359
  },
  {
    "time": 1768677300000,
    "open": 0.31605,
    "high": 0.31637,
    "low": 0.31564,
    "close": 0.31632,
    "volume": 235
  },
  {
    "time": 1768678200000,
    "open": 0.31633,
    "high": 0.31658,
    "low": 0.31632,
    "close": 0.31656,
    "volume": 212
  },
  {
    "time": 1768679100000,
    "open": 0.31646,
    "high": 0.31665,
    "low": 0.31633,
    "close": 0.31653,
    "volume": 218
  },
  {
    "time": 1768680000000,
    "open": 0.31648,
    "high": 0.31693,
    "low": 0.31623,
    "close": 0.31693,
    "volume": 973
  },
  {
    "time": 1768680900000,
    "open": 0.31692,
    "high": 0.31796,
    "low": 0.31688,
    "close": 0.3173,
    "volume": 1165
  },
  {
    "time": 1768681800000,
    "open": 0.3173,
    "high": 0.3173,
    "low": 0.31666,
    "close": 0.31709,
    "volume": 817
  },
  {
    "time": 1768682700000,
    "open": 0.31709,
    "high": 0.31773,
    "low": 0.31697,
    "close": 0.31771,
    "volume": 311
  },
  {
    "time": 1768683600000,
    "open": 0.3177,
    "high": 0.31805,
    "low": 0.3174,
    "close": 0.31803,
    "volume": 1738
  },
  {
    "time": 1768684500000,
    "open": 0.31807,
    "high": 0.31863,
    "low": 0.31807,
    "close": 0.31846,
    "volume": 346
  },
  {
    "time": 1768685400000,
    "open": 0.31847,
    "high": 0.31847,
    "low": 0.31811,
    "close": 0.31833,
    "volume": 350
  },
  {
    "time": 1768686300000,
    "open": 0.31833,
    "high": 0.31861,
    "low": 0.31829,
    "close": 0.31841,
    "volume": 342
  },
  {
    "time": 1768687200000,
    "open": 0.31854,
    "high": 0.31899,
    "low": 0.31854,
    "close": 0.31878,
    "volume": 300
  },
  {
    "time": 1768688100000,
    "open": 0.31892,
    "high": 0.31904,
    "low": 0.3188,
    "close": 0.31889,
    "volume": 419
  },
  {
    "time": 1768689000000,
    "open": 0.31898,
    "high": 0.3191,
    "low": 0.31844,
    "close": 0.31854,
    "volume": 534
  },
  {
    "time": 1768689900000,
    "open": 0.31864,
    "high": 0.31873,
    "low": 0.318,
    "close": 0.31836,
    "volume": 1755
  },
  {
    "time": 1768690800000,
    "open": 0.31842,
    "high": 0.31886,
    "low": 0.31831,
    "close": 0.31859,
    "volume": 429
  },
  {
    "time": 1768691700000,
    "open": 0.31852,
    "high": 0.31882,
    "low": 0.31852,
    "close": 0.31869,
    "volume": 269
  },
  {
    "time": 1768692600000,
    "open": 0.31886,
    "high": 0.31962,
    "low": 0.31832,
    "close": 0.31866,
    "volume": 1344
  },
  {
    "time": 1768693500000,
    "open": 0.31869,
    "high": 0.31872,
    "low": 0.3179,
    "close": 0.31856,
    "volume": 1728
  },
  {
    "time": 1768694400000,
    "open": 0.31859,
    "high": 0.31924,
    "low": 0.3175,
    "close": 0.31826,
    "volume": 1588
  },
  {
    "time": 1768695300000,
    "open": 0.31821,
    "high": 0.31891,
    "low": 0.31769,
    "close": 0.31774,
    "volume": 760
  },
  {
    "time": 1768696200000,
    "open": 0.31784,
    "high": 0.31784,
    "low": 0.31692,
    "close": 0.31729,
    "volume": 723
  },
  {
    "time": 1768697100000,
    "open": 0.31732,
    "high": 0.31767,
    "low": 0.31694,
    "close": 0.31731,
    "volume": 987
  },
  {
    "time": 1768698000000,
    "open": 0.3174,
    "high": 0.31752,
    "low": 0.31714,
    "close": 0.31743,
    "volume": 276
  },
  {
    "time": 1768698900000,
    "open": 0.31736,
    "high": 0.3177,
    "low": 0.31733,
    "close": 0.31765,
    "volume": 393
  },
  {
    "time": 1768699800000,
    "open": 0.3175,
    "high": 0.31768,
    "low": 0.31735,
    "close": 0.31761,
    "volume": 433
  },
  {
    "time": 1768700700000,
    "open": 0.31761,
    "high": 0.31809,
    "low": 0.31761,
    "close": 0.31805,
    "volume": 458
  },
  {
    "time": 1768701600000,
    "open": 0.31807,
    "high": 0.31907,
    "low": 0.31791,
    "close": 0.31877,
    "volume": 711
  },
  {
    "time": 1768702500000,
    "open": 0.31883,
    "high": 0.31934,
    "low": 0.31883,
    "close": 0.31934,
    "volume": 213
  },
  {
    "time": 1768703400000,
    "open": 0.31931,
    "high": 0.31931,
    "low": 0.31805,
    "close": 0.31814,
    "volume": 860
  },
  {
    "time": 1768704300000,
    "open": 0.31821,
    "high": 0.31894,
    "low": 0.3182,
    "close": 0.3189,
    "volume": 194
  },
  {
    "time": 1768705200000,
    "open": 0.3188,
    "high": 0.31908,
    "low": 0.31874,
    "close": 0.31905,
    "volume": 109
  },
  {
    "time": 1768706100000,
    "open": 0.31906,
    "high": 0.31996,
    "low": 0.31905,
    "close": 0.31996,
    "volume": 185
  },
  {
    "time": 1768707000000,
    "open": 0.31997,
    "high": 0.32012,
    "low": 0.31979,
    "close": 0.3199,
    "volume": 658
  },
  {
    "time": 1768707900000,
    "open": 0.31988,
    "high": 0.32034,
    "low": 0.31988,
    "close": 0.32032,
    "volume": 1107
  },
  {
    "time": 1768708800000,
    "open": 0.32031,
    "high": 0.3204,
    "low": 0.31917,
    "close": 0.31947,
    "volume": 342
  },
  {
    "time": 1768709700000,
    "open": 0.31961,
    "high": 0.31961,
    "low": 0.31871,
    "close": 0.31929,
    "volume": 1401
  },
  {
    "time": 1768710600000,
    "open": 0.31921,
    "high": 0.31952,
    "low": 0.31903,
    "close": 0.31922,
    "volume": 115
  },
  {
    "time": 1768711500000,
    "open": 0.31916,
    "high": 0.31955,
    "low": 0.31907,
    "close": 0.31943,
    "volume": 183
  },
  {
    "time": 1768712400000,
    "open": 0.31942,
    "high": 0.32009,
    "low": 0.31942,
    "close": 0.31997,
    "volume": 166
  },
  {
    "time": 1768713300000,
    "open": 0.32004,
    "high": 0.32059,
    "low": 0.32001,
    "close": 0.32011,
    "volume": 635
  },
  {
    "time": 1768714200000,
    "open": 0.32011,
    "high": 0.32063,
    "low": 0.32005,
    "close": 0.32055,
    "volume": 397
  },
  {
    "time": 1768715100000,
    "open": 0.32054,
    "high": 0.32091,
    "low": 0.32052,
    "close": 0.32058,
    "volume": 269
  },
  {
    "time": 1768716000000,
    "open": 0.32062,
    "high": 0.3207,
    "low": 0.31996,
    "close": 0.31999,
    "volume": 379
  },
  {
    "time": 1768716900000,
    "open": 0.31997,
    "high": 0.32003,
    "low": 0.31938,
    "close": 0.31966,
    "volume": 1146
  },
  {
    "time": 1768717800000,
    "open": 0.31955,
    "high": 0.31979,
    "low": 0.31922,
    "close": 0.3193,
    "volume": 326
  },
  {
    "time": 1768718700000,
    "open": 0.31927,
    "high": 0.31986,
    "low": 0.31917,
    "close": 0.31964,
    "volume": 306
  },
  {
    "time": 1768719600000,
    "open": 0.31962,
    "high": 0.3199,
    "low": 0.31962,
    "close": 0.31989,
    "volume": 333
  },
  {
    "time": 1768720500000,
    "open": 0.3199,
    "high": 0.32,
    "low": 0.31981,
    "close": 0.32,
    "volume": 117
  },
  {
    "time": 1768721400000,
    "open": 0.31992,
    "high": 0.31994,
    "low": 0.31852,
    "close": 0.31887,
    "volume": 895
  },
  {
    "time": 1768722300000,
    "open": 0.31888,
    "high": 0.319,
    "low": 0.31805,
    "close": 0.31828,
    "volume": 887
  },
  {
    "time": 1768723200000,
    "open": 0.31821,
    "high": 0.31824,
    "low": 0.31626,
    "close": 0.31698,
    "volume": 2480
  },
  {
    "time": 1768724100000,
    "open": 0.31683,
    "high": 0.31733,
    "low": 0.3164,
    "close": 0.31643,
    "volume": 486
  },
  {
    "time": 1768725000000,
    "open": 0.3165,
    "high": 0.31651,
    "low": 0.31495,
    "close": 0.31552,
    "volume": 1756
  },
  {
    "time": 1768725900000,
    "open": 0.31546,
    "high": 0.31582,
    "low": 0.31525,
    "close": 0.31545,
    "volume": 575
  },
  {
    "time": 1768726800000,
    "open": 0.31543,
    "high": 0.31623,
    "low": 0.31493,
    "close": 0.3151,
    "volume": 2507
  },
  {
    "time": 1768727700000,
    "open": 0.31513,
    "high": 0.31618,
    "low": 0.31512,
    "close": 0.31617,
    "volume": 346
  },
  {
    "time": 1768728600000,
    "open": 0.31616,
    "high": 0.31668,
    "low": 0.31611,
    "close": 0.31665,
    "volume": 667
  },
  {
    "time": 1768729500000,
    "open": 0.31668,
    "high": 0.31702,
    "low": 0.31637,
    "close": 0.31698,
    "volume": 320
  },
  {
    "time": 1768730400000,
    "open": 0.31702,
    "high": 0.31735,
    "low": 0.3166,
    "close": 0.31678,
    "volume": 663
  },
  {
    "time": 1768731300000,
    "open": 0.31682,
    "high": 0.31703,
    "low": 0.31662,
    "close": 0.31701,
    "volume": 364
  },
  {
    "time": 1768732200000,
    "open": 0.31701,
    "high": 0.3173,
    "low": 0.31698,
    "close": 0.31715,
    "volume": 514
  },
  {
    "time": 1768733100000,
    "open": 0.31715,
    "high": 0.31746,
    "low": 0.31715,
    "close": 0.31729,
    "volume": 153
  },
  {
    "time": 1768734000000,
    "open": 0.31718,
    "high": 0.31799,
    "low": 0.31718,
    "close": 0.31792,
    "volume": 464
  },
  {
    "time": 1768734900000,
    "open": 0.31798,
    "high": 0.31807,
    "low": 0.31676,
    "close": 0.31741,
    "volume": 464
  },
  {
    "time": 1768735800000,
    "open": 0.31735,
    "high": 0.31788,
    "low": 0.31719,
    "close": 0.31767,
    "volume": 298
  },
  {
    "time": 1768736700000,
    "open": 0.31768,
    "high": 0.31768,
    "low": 0.31717,
    "close": 0.31734,
    "volume": 340
  },
  {
    "time": 1768737600000,
    "open": 0.31725,
    "high": 0.31735,
    "low": 0.3159,
    "close": 0.3162,
    "volume": 1134
  },
  {
    "time": 1768738500000,
    "open": 0.3162,
    "high": 0.3162,
    "low": 0.31569,
    "close": 0.3157,
    "volume": 171
  },
  {
    "time": 1768739400000,
    "open": 0.3157,
    "high": 0.31601,
    "low": 0.31556,
    "close": 0.31601,
    "volume": 191
  },
  {
    "time": 1768740300000,
    "open": 0.31601,
    "high": 0.31607,
    "low": 0.31568,
    "close": 0.31606,
    "volume": 234
  },
  {
    "time": 1768741200000,
    "open": 0.31601,
    "high": 0.31618,
    "low": 0.31591,
    "close": 0.31602,
    "volume": 198
  },
  {
    "time": 1768742100000,
    "open": 0.31609,
    "high": 0.31609,
    "low": 0.31539,
    "close": 0.31601,
    "volume": 311
  },
  {
    "time": 1768743000000,
    "open": 0.31601,
    "high": 0.3167,
    "low": 0.31582,
    "close": 0.3167,
    "volume": 272
  },
  {
    "time": 1768743900000,
    "open": 0.31674,
    "high": 0.31697,
    "low": 0.31662,
    "close": 0.31689,
    "volume": 163
  },
  {
    "time": 1768744800000,
    "open": 0.31689,
    "high": 0.31705,
    "low": 0.3167,
    "close": 0.31685,
    "volume": 149
  },
  {
    "time": 1768745700000,
    "open": 0.31678,
    "high": 0.31769,
    "low": 0.3163,
    "close": 0.31764,
    "volume": 344
  },
  {
    "time": 1768746600000,
    "open": 0.31775,
    "high": 0.31891,
    "low": 0.31774,
    "close": 0.3185,
    "volume": 1721
  },
  {
    "time": 1768747500000,
    "open": 0.31852,
    "high": 0.31873,
    "low": 0.31796,
    "close": 0.31873,
    "volume": 1408
  },
  {
    "time": 1768748400000,
    "open": 0.31874,
    "high": 0.3195,
    "low": 0.31868,
    "close": 0.31934,
    "volume": 523
  },
  {
    "time": 1768749300000,
    "open": 0.31934,
    "high": 0.31944,
    "low": 0.319,
    "close": 0.3194,
    "volume": 360
  },
  {
    "time": 1768750200000,
    "open": 0.31939,
    "high": 0.31984,
    "low": 0.31929,
    "close": 0.31978,
    "volume": 379
  },
  {
    "time": 1768751100000,
    "open": 0.31969,
    "high": 0.31984,
    "low": 0.3194,
    "close": 0.31962,
    "volume": 182
  },
  {
    "time": 1768752000000,
    "open": 0.31963,
    "high": 0.31996,
    "low": 0.31908,
    "close": 0.31992,
    "volume": 261
  },
  {
    "time": 1768752900000,
    "open": 0.31992,
    "high": 0.31995,
    "low": 0.31926,
    "close": 0.31938,
    "volume": 1117
  },
  {
    "time": 1768753800000,
    "open": 0.31932,
    "high": 0.31947,
    "low": 0.31881,
    "close": 0.31881,
    "volume": 211
  },
  {
    "time": 1768754700000,
    "open": 0.31877,
    "high": 0.31909,
    "low": 0.31867,
    "close": 0.31885,
    "volume": 274
  },
  {
    "time": 1768755600000,
    "open": 0.31886,
    "high": 0.31909,
    "low": 0.3186,
    "close": 0.3186,
    "volume": 284
  },
  {
    "time": 1768756500000,
    "open": 0.31865,
    "high": 0.31878,
    "low": 0.31834,
    "close": 0.31878,
    "volume": 272
  },
  {
    "time": 1768757400000,
    "open": 0.31874,
    "high": 0.31891,
    "low": 0.31828,
    "close": 0.31842,
    "volume": 1557
  },
  {
    "time": 1768758300000,
    "open": 0.31855,
    "high": 0.31876,
    "low": 0.31845,
    "close": 0.31868,
    "volume": 183
  },
  {
    "time": 1768759200000,
    "open": 0.31867,
    "high": 0.31932,
    "low": 0.31867,
    "close": 0.31903,
    "volume": 268
  },
  {
    "time": 1768760100000,
    "open": 0.31903,
    "high": 0.32021,
    "low": 0.31903,
    "close": 0.32007,
    "volume": 1733
  },
  {
    "time": 1768761000000,
    "open": 0.32011,
    "high": 0.32023,
    "low": 0.31972,
    "close": 0.31984,
    "volume": 300
  },
  {
    "time": 1768761900000,
    "open": 0.3198,
    "high": 0.32013,
    "low": 0.31972,
    "close": 0.31996,
    "volume": 189
  },
  {
    "time": 1768762800000,
    "open": 0.31995,
    "high": 0.32006,
    "low": 0.31977,
    "close": 0.31982,
    "volume": 211
  },
  {
    "time": 1768763700000,
    "open": 0.31982,
    "high": 0.31982,
    "low": 0.31923,
    "close": 0.31927,
    "volume": 355
  },
  {
    "time": 1768764600000,
    "open": 0.31923,
    "high": 0.31929,
    "low": 0.31868,
    "close": 0.31886,
    "volume": 530
  },
  {
    "time": 1768765500000,
    "open": 0.31904,
    "high": 0.31904,
    "low": 0.31859,
    "close": 0.31889,
    "volume": 290
  },
  {
    "time": 1768766400000,
    "open": 0.31889,
    "high": 0.3196,
    "low": 0.31888,
    "close": 0.3196,
    "volume": 349
  },
  {
    "time": 1768767300000,
    "open": 0.31959,
    "high": 0.31967,
    "low": 0.31942,
    "close": 0.31967,
    "volume": 198
  },
  {
    "time": 1768768200000,
    "open": 0.31964,
    "high": 0.32018,
    "low": 0.31964,
    "close": 0.32015,
    "volume": 229
  },
  {
    "time": 1768769100000,
    "open": 0.32012,
    "high": 0.32056,
    "low": 0.32012,
    "close": 0.32048,
    "volume": 553
  },
  {
    "time": 1768770000000,
    "open": 0.32048,
    "high": 0.32056,
    "low": 0.31987,
    "close": 0.31999,
    "volume": 381
  }
]