[
  {
    "time": 1768662900000,
    "open": 0.01082,
    "high": 0.01116,
    "low": 0.01047,
    "close": 0.0108,
    "volume": 1263860
  },
  {
    "time": 1768663800000,
    "open": 0.01082,
    "high": 0.01256,
    "low": 0.01082,
    "close": 0.01209,
    "volume": 1237996
  },
  {
    "time": 1768664700000,
    "open": 0.0122,
    "high": 0.01491,
    "low": 0.01217,
    "close": 0.01376,
    "volume": 2354988
  },
  {
    "time": 1768665600000,
    "open": 0.0137,
    "high": 0.01469,
    "low": 0.01236,
    "close": 0.01377,
    "volume": 2414684
  },
  {
    "time": 1768666500000,
    "open": 0.01377,
    "high": 0.01591,
    "low": 0.01322,
    "close": 0.01581,
    "volume": 1761924
  },
  {
    "time": 1768667400000,
    "open": 0.01582,
    "high": 0.01685,
    "low": 0.01538,
    "close": 0.01659,
    "volume": 1247126
  },
  {
    "time": 1768668300000,
    "open": 0.01662,
    "high": 0.02316,
    "low": 0.0162,
    "close": 0.01971,
    "volume": 1706567
  },
  {
    "time": 1768669200000,
    "open": 0.01966,
    "high": 0.02416,
    "low": 0.01899,
    "close": 0.02309,
    "volume": 1661667
  },
  {
    "time": 1768670100000,
    "open": 0.02318,
    "high": 0.02829,
    "low": 0.02124,
    "close": 0.02466,
    "volume": 2121511
  },
  {
    "time": 1768671000000,
    "open": 0.02468,
    "high": 0.0279,
    "low": 0.02157,
    "close": 0.02637,
    "volume": 1361194
  },
  {
    "time": 1768671900000,
    "open": 0.02623,
    "high": 0.02646,
    "low": 0.02253,
    "close": 0.02388,
    "volume": 1662523
  },
  {
    "time": 1768672800000,
    "open": 0.0238,
    "high": 0.02412,
    "low": 0.01585,
    "close": 0.01866,
    "volume": 2857072
  },
  {
    "time": 1768673700000,
    "open": 0.01867,
    "high": 0.02301,
    "low": 0.01682,
    "close": 0.01688,
    "volume": 2402399
  },
  {
    "time": 1768674600000,
    "open": 0.01713,
    "high": 0.01755,
    "low": 0.01155,
    "close": 0.01155,
    "volume": 3252055
  },
  {
    "time": 1768675500000,
    "open": 0.01162,
    "high": 0.01215,
    "low": 0.01052,
    "close": 0.01165,
    "volume": 2896524
  },
  {
    "time": 1768676400000,
    "open": 0.01167,
    "high": 0.01206,
    "low": 0.01088,
    "close": 0.01173,
    "volume": 757396
  },
  {
    "time": 1768677300000,
    "open": 0.01172,
    "high": 0.01232,
    "low": 0.01134,
    "close": 0.01197,
    "volume": 1198379
  },
  {
    "time": 1768678200000,
    "open": 0.01201,
    "high": 0.01217,
    "low": 0.01145,
    "close": 0.01194,
    "volume": 696319
  },
  {
    "time": 1768679100000,
    "open": 0.01193,
    "high": 0.01278,
    "low": 0.01179,
    "close": 0.01261,
    "volume": 598047
  },
  {
    "time": 1768680000000,
    "open": 0.01264,
    "high": 0.01264,
    "low": 0.01189,
    "close": 0.01196,
    "volume": 615727
  },
  {
    "time": 1768680900000,
    "open": 0.01197,
    "high": 0.01247,
    "low": 0.01125,
    "close": 0.01125,
    "volume": 619485
  },
  {
    "time": 1768681800000,
    "open": 0.01128,
    "high": 0.01193,
    "low": 0.01113,
    "close": 0.01178,
    "volume": 567300
  },
  {
    "time": 1768682700000,
    "open": 0.01176,
    "high": 0.01194,
    "low": 0.01167,
    "close": 0.01174,
    "volume": 439368
  },
  {
    "time": 1768683600000,
    "open": 0.01173,
    "high": 0.01187,
    "low": 0.01145,
    "close": 0.01152,
    "volume": 549757
  },
  {
    "time": 1768684500000,
    "open": 0.01151,
    "high": 0.01174,
    "low": 0.01145,
    "close": 0.0117,
    "volume": 499443
  },
  {
    "time": 1768685400000,
    "open": 0.0117,
    "high": 0.01209,
    "low": 0.01151,
    "close": 0.01186,
    "volume": 560732
  },
  {
    "time": 1768686300000,
    "open": 0.01187,
    "high": 0.0126,
    "low": 0.01178,
    "close": 0.01233,
    "volume": 565835
  },
  {
    "time": 1768687200000,
    "open": 0.01232,
    "high": 0.01318,
    "low": 0.01113,
    "close": 0.01142,
    "volume": 1037263
  },
  {
    "time": 1768688100000,
    "open": 0.01141,
    "high": 0.01183,
    "low": 0.01066,
    "close": 0.01147,
    "volume": 505992
  },
  {
    "time": 1768689000000,
    "open": 0.01139,
    "high": 0.01159,
    "low": 0.01113,
    "close": 0.01144,
    "volume": 493529
  },
  {
    "time": 1768689900000,
    "open": 0.01136,
    "high": 0.01161,
    "low": 0.01114,
    "close": 0.01161,
    "volume": 476308
  },
  {
    "time": 1768690800000,
    "open": 0.01152,
    "high": 0.01168,
    "low": 0.01115,
    "close": 0.01124,
    "volume": 531002
  },
  {
    "time": 1768691700000,
    "open": 0.01126,
    "high": 0.01131,
    "low": 0.01108,
    "close": 0.01118,
    "volume": 436088
  },
  {
    "time": 1768692600000,
    "open": 0.01117,
    "high": 0.01128,
    "low": 0.01106,
    "close": 0.01111,
    "volume": 373845
  },
  {
    "time": 1768693500000,
    "open": 0.01108,
    "high": 0.01118,
    "low": 0.01081,
    "close": 0.01093,
    "volume": 395781
  },
  {
    "time": 1768694400000,
    "open": 0.01093,
    "high": 0.01143,
    "low": 0.01083,
    "close": 0.01139,
    "volume": 469864
  },
  {
    "time": 1768695300000,
    "open": 0.01137,
    "high": 0.01173,
    "low": 0.01134,
    "close": 0.01151,
    "volume": 447796
  },
  {
    "time": 1768696200000,
    "open": 0.01152,
    "high": 0.0116,
    "low": 0.01136,
    "close": 0.01153,
    "volume": 414574
  },
  {
    "time": 1768697100000,
    "open": 0.01153,
    "high": 0.01155,
    "low": 0.01135,
    "close": 0.01148,
    "volume": 416412
  },
  {
    "time": 1768698000000,
    "open": 0.01148,
    "high": 0.01155,
    "low": 0.01132,
    "close": 0.01147,
    "volume": 394734
  },
  {
    "time": 1768698900000,
    "open": 0.01146,
    "high": 0.01147,
    "low": 0.0113,
    "close": 0.01137,
    "volume": 321053
  },
  {
    "time": 1768699800000,
    "open": 0.01135,
    "high": 0.01136,
    "low": 0.01116,
    "close": 0.01121,
    "volume": 375830
  },
  {
    "time": 1768700700000,
    "open": 0.01122,
    "high": 0.01126,
    "low": 0.01076,
    "close": 0.01104,
    "volume": 548522
  },
  {
    "time": 1768701600000,
    "open": 0.01106,
    "high": 0.01137,
    "low": 0.01021,
    "close": 0.01117,
    "volume": 1000064
  },
  {
    "time": 1768702500000,
    "open": 0.01112,
    "high": 0.01219,
    "low": 0.01103,
    "close": 0.01196,
    "volume": 713360
  },
  {
    "time": 1768703400000,
    "open": 0.01194,
    "high": 0.01244,
    "low": 0.01117,
    "close": 0.01149,
    "volume": 739523
  },
  {
    "time": 1768704300000,
    "open": 0.01154,
    "high": 0.0122,
    "low": 0.01104,
    "close": 0.01152,
    "volume": 797010
  },
  {
    "time": 1768705200000,
    "open": 0.01155,
    "high": 0.01183,
    "low": 0.01128,
    "close": 0.0117,
    "volume": 688615
  },
  {
    "time": 1768706100000,
    "open": 0.01172,
    "high": 0.01185,
    "low": 0.01158,
    "close": 0.0118,
    "volume": 454106
  },
  {
    "time": 1768707000000,
    "open": 0.0118,
    "high": 0.01187,
    "low": 0.01127,
    "close": 0.01142,
    "volume": 839597
  },
  {
    "time": 1768707900000,
    "open": 0.01141,
    "high": 0.01152,
    "low": 0.01119,
    "close": 0.01136,
    "volume": 370152
  },
  {
    "time": 1768708800000,
    "open": 0.01134,
    "high": 0.01146,
    "low": 0.01128,
    "close": 0.01137,
    "volume": 356021
  },
  {
    "time": 1768709700000,
    "open": 0.01135,
    "high": 0.0116,
    "low": 0.01124,
    "close": 0.01147,
    "volume": 444594
  },
  {
    "time": 1768710600000,
    "open": 0.01146,
    "high": 0.01158,
    "low": 0.01143,
    "close": 0.01156,
    "volume": 342770
  },
  {
    "time": 1768711500000,
    "open": 0.01155,
    "high": 0.01172,
    "low": 0.01134,
    "close": 0.01142,
    "volume": 327595
  },
  {
    "time": 1768712400000,
    "open": 0.01139,
    "high": 0.01159,
    "low": 0.01107,
    "close": 0.01122,
    "volume": 483508
  },
  {
    "time": 1768713300000,
    "open": 0.01122,
    "high": 0.01142,
    "low": 0.01119,
    "close": 0.01133,
    "volume": 342271
  },
  {
    "time": 1768714200000,
    "open": 0.01134,
    "high": 0.01154,
    "low": 0.01131,
    "close": 0.0115,
    "volume": 398084
  },
  {
    "time": 1768715100000,
    "open": 0.01148,
    "high": 0.01158,
    "low": 0.0114,
    "close": 0.01151,
    "volume": 283664
  },
  {
    "time": 1768716000000,
    "open": 0.0115,
    "high": 0.01156,
    "low": 0.01124,
    "close": 0.01132,
    "volume": 430831
  },
  {
    "time": 1768716900000,
    "open": 0.01132,
    "high": 0.01141,
    "low": 0.01123,
    "close": 0.0113,
    "volume": 358630
  },
  {
    "time": 1768717800000,
    "open": 0.0113,
    "high": 0.01154,
    "low": 0.01128,
    "close": 0.01148,
    "volume": 290489
  },
  {
    "time": 1768718700000,
    "open": 0.01148,
    "high": 0.01151,
    "low": 0.01138,
    "close": 0.01138,
    "volume": 330940
  },
  {
    "time": 1768719600000,
    "open": 0.01138,
    "high": 0.0114,
    "low": 0.01114,
    "close": 0.01118,
    "volume": 331015
  },
  {
    "time": 1768720500000,
    "open": 0.01117,
    "high": 0.01134,
    "low": 0.01117,
    "close": 0.01132,
    "volume": 401202
  },
  {
    "time": 1768721400000,
    "open": 0.01131,
    "high": 0.01139,
    "low": 0.01092,
    "close": 0.01129,
    "volume": 455907
  },
  {
    "time": 1768722300000,
    "open": 0.01128,
    "high": 0.01134,
    "low": 0.01109,
    "close": 0.0111,
    "volume": 472623
  },
  {
    "time": 1768723200000,
    "open": 0.01109,
    "high": 0.01114,
    "low": 0.01093,
    "close": 0.01097,
    "volume": 518049
  },
  {
    "time": 1768724100000,
    "open": 0.01097,
    "high": 0.01149,
    "low": 0.01093,
    "close": 0.01141,
    "volume": 469609
  },
  {
    "time": 1768725000000,
    "open": 0.01141,
    "high": 0.01174,
    "low": 0.01123,
    "close": 0.01136,
    "volume": 518234
  },
  {
    "time": 1768725900000,
    "open": 0.01133,
    "high": 0.01145,
    "low": 0.01133,
    "close": 0.01138,
    "volume": 303898
  },
  {
    "time": 1768726800000,
    "open": 0.01139,
    "high": 0.01162,
    "low": 0.01128,
    "close": 0.01154,
    "volume": 310050
  },
  {
    "time": 1768727700000,
    "open": 0.01156,
    "high": 0.01156,
    "low": 0.01138,
    "close": 0.01142,
    "volume": 307518
  },
  {
    "time": 1768728600000,
    "open": 0.01142,
    "high": 0.01163,
    "low": 0.01142,
    "close": 0.01161,
    "volume": 283772
  },
  {
    "time": 1768729500000,
    "open": 0.01161,
    "high": 0.01201,
    "low": 0.01159,
    "close": 0.01196,
    "volume": 339127
  },
  {
    "time": 1768730400000,
    "open": 0.01196,
    "high": 0.01265,
    "low": 0.01195,
    "close": 0.0124,
    "volume": 714396
  },
  {
    "time": 1768731300000,
    "open": 0.0124,
    "high": 0.01295,
    "low": 0.01228,
    "close": 0.01294,
    "volume": 601029
  },
  {
    "time": 1768732200000,
    "open": 0.01296,
    "high": 0.01351,
    "low": 0.0122,
    "close": 0.01223,
    "volume": 571429
  },
  {
    "time": 1768733100000,
    "open": 0.01227,
    "high": 0.01238,
    "low": 0.01192,
    "close": 0.01218,
    "volume": 442466
  },
  {
    "time": 1768734000000,
    "open": 0.01218,
    "high": 0.01239,
    "low": 0.01218,
    "close": 0.01235,
    "volume": 289157
  },
  {
    "time": 1768734900000,
    "open": 0.01235,
    "high": 0.01258,
    "low": 0.01224,
    "close": 0.0125,
    "volume": 318510
  },
  {
    "time": 1768735800000,
    "open": 0.01248,
    "high": 0.01283,
    "low": 0.01246,
    "close": 0.01274,
    "volume": 473962
  },
  {
    "time": 1768736700000,
    "open": 0.01273,
    "high": 0.01291,
    "low": 0.01228,
    "close": 0.01269,
    "volume": 494578
  },
  {
    "time": 1768737600000,
    "open": 0.01267,
    "high": 0.01293,
    "low": 0.0122,
    "close": 0.01262,
    "volume": 470937
  },
  {
    "time": 1768738500000,
    "open": 0.01261,
    "high": 0.0127,
    "low": 0.01252,
    "close": 0.01263,
    "volume": 346836
  },
  {
    "time": 1768739400000,
    "open": 0.01266,
    "high": 0.01273,
    "low": 0.01131,
    "close": 0.01196,
    "volume": 833274
  },
  {
    "time": 1768740300000,
    "open": 0.01197,
    "high": 0.01223,
    "low": 0.01176,
    "close": 0.0121,
    "volume": 398763
  },
  {
    "time": 1768741200000,
    "open": 0.01208,
    "high": 0.0126,
    "low": 0.01199,
    "close": 0.0126,
    "volume": 443451
  },
  {
    "time": 1768742100000,
    "open": 0.01257,
    "high": 0.01286,
    "low": 0.01241,
    "close": 0.01269,
    "volume": 453530
  },
  {
    "time": 1768743000000,
    "open": 0.01268,
    "high": 0.01286,
    "low": 0.01202,
    "close": 0.0125,
    "volume": 493222
  },
  {
    "time": 1768743900000,
    "open": 0.01251,
    "high": 0.0127,
    "low": 0.01245,
    "close": 0.01262,
    "volume": 388900
  },
  {
    "time": 1768744800000,
    "open": 0.01262,
    "high": 0.01275,
    "low": 0.01229,
    "close": 0.01254,
    "volume": 434919
  },
  {
    "time": 1768745700000,
    "open": 0.01253,
    "high": 0.01273,
    "low": 0.01235,
    "close": 0.01256,
    "volume": 386058
  },
  {
    "time": 1768746600000,
    "open": 0.01259,
    "high": 0.01263,
    "low": 0.01231,
    "close": 0.0125,
    "volume": 293111
  },
  {
    "time": 1768747500000,
    "open": 0.01246,
    "high": 0.01262,
    "low": 0.01238,
    "close": 0.01243,
    "volume": 267337
  },
  {
    "time": 1768748400000,
    "open": 0.01242,
    "high": 0.01255,
    "low": 0.01216,
    "close": 0.01235,
    "volume": 324939
  },
  {
    "time": 1768749300000,
    "open": 0.01236,
    "high": 0.0124,
    "low": 0.01176,
    "close": 0.01185,
    "volume": 484157
  },
  {
    "time": 1768750200000,
    "open": 0.01186,
    "high": 0.01197,
    "low": 0.01159,
    "close": 0.01164,
    "volume": 458689
  },
  {
    "time": 1768751100000,
    "open": 0.01165,
    "high": 0.01187,
    "low": 0.01158,
    "close": 0.0117,
    "volume": 419409
  },
  {
    "time": 1768752000000,
    "open": 0.01173,
    "high": 0.01189,
    "low": 0.01164,
    "close": 0.01175,
    "volume": 336635
  },
  {
    "time": 1768752900000,
    "open": 0.01174,
    "high": 0.0118,
    "low": 0.01158,
    "close": 0.01162,
    "volume": 387262
  },
  {
    "time": 1768753800000,
    "open": 0.0116,
    "high": 0.01175,
    "low": 0.01156,
    "close": 0.01164,
    "volume": 359460
  },
  {
    "time": 1768754700000,
    "open": 0.01164,
    "high": 0.01179,
    "low": 0.0114,
    "close": 0.01161,
    "volume": 383203
  },
  {
    "time": 1768755600000,
    "open": 0.01161,
    "high": 0.01165,
    "low": 0.01135,
    "close": 0.01148,
    "volume": 390483
  },
  {
    "time": 1768756500000,
    "open": 0.01147,
    "high": 0.01165,
    "low": 0.01147,
    "close": 0.01157,
    "volume": 378281
  },
  {
    "time": 1768757400000,
    "open": 0.01157,
    "high": 0.01158,
    "low": 0.01125,
    "close": 0.01141,
    "volume": 332873
  },
  {
    "time": 1768758300000,
    "open": 0.01141,
    "high": 0.01149,
    "low": 0.0112,
    "close": 0.01135,
    "volume": 394412
  },
  {
    "time": 1768759200000,
    "open": 0.01134,
    "high": 0.01136,
    "low": 0.01121,
    "close": 0.01127,
    "volume": 331690
  },
  {
    "time": 1768760100000,
    "open": 0.01128,
    "high": 0.01146,
    "low": 0.01107,
    "close": 0.01136,
    "volume": 523084
  },
  {
    "time": 1768761000000,
    "open": 0.01137,
    "high": 0.01159,
    "low": 0.01112,
    "close": 0.01114,
    "volume": 535211
  },
  {
    "time": 1768761900000,
    "open": 0.01114,
    "high": 0.01125,
    "low": 0.01114,
    "close": 0.01119,
    "volume": 299256
  },
  {
    "time": 1768762800000,
    "open": 0.01118,
    "high": 0.01126,
    "low": 0.01104,
    "close": 0.01114,
    "volume": 304161
  },
  {
    "time": 1768763700000,
    "open": 0.01114,
    "high": 0.01117,
    "low": 0.0111,
    "close": 0.01116,
    "volume": 294426
  },
  {
    "time": 1768764600000,
    "open": 0.01116,
    "high": 0.01125,
    "low": 0.01106,
    "close": 0.01109,
    "volume": 356255
  },
  {
    "time": 1768765500000,
    "open": 0.01109,
    "high": 0.01119,
    "low": 0.01102,
    "close": 0.01103,
    "volume": 484795
  },
  {
    "time": 1768766400000,
    "open": 0.01102,
    "high": 0.01108,
    "low": 0.01092,
    "close": 0.01102,
    "volume": 408334
  },
  {
    "time": 1768767300000,
    "open": 0.011,
    "high": 0.01105,
    "low": 0.01095,
    "close": 0.01104,
    "volume": 290937
  },
  {
    "time": 1768768200000,
    "open": 0.01105,
    "high": 0.01108,
    "low": 0.01103,
    "close": 0.01105,
    "volume": 208120
  },
  {
    "time": 1768769100000,
    "open": 0.01106,
    "high": 0.01106,
    "low": 0.01084,
    "close": 0.01087,
    "volume": 223356
  },
  {
    "time": 1768770000000,
    "open": 0.01088,
    "high": 0.01096,
    "low": 0.01085,
    "close": 0.01086,
    "volume": 272527
  },
  {
    "time": 1768770900000,
    "open": 0.01086,
    "high": 0.01093,
    "low": 0.01079,
    "close": 0.01093,
    "volume": 223802
  },
  {
    "time": 1768771800000,
    "open": 0.01093,
    "high": 0.01118,
    "low": 0.01038,
    "close": 0.01107,
    "volume": 738437
  },
  {
    "time": 1768772700000,
    "open": 0.01104,
    "high": 0.0111,
    "low": 0.01073,
    "close": 0.01077,
    "volume": 521611
  },
  {
    "time": 1768773600000,
    "open": 0.01076,
    "high": 0.01092,
    "low": 0.01068,
    "close": 0.01089,
    "volume": 404388
  },
  {
    "time": 1768774500000,
    "open": 0.01089,
    "high": 0.01102,
    "low": 0.01057,
    "close": 0.01102,
    "volume": 448322
  },
  {
    "time": 1768775400000,
    "open": 0.01102,
    "high": 0.0111,
    "low": 0.01078,
    "close": 0.01082,
    "volume": 475360
  },
  {
    "time": 1768776300000,
    "open": 0.0108,
    "high": 0.0109,
    "low": 0.01043,
    "close": 0.0108,
    "volume": 545415
  },
  {
    "time": 1768777200000,
    "open": 0.0108,
    "high": 0.01086,
    "low": 0.01072,
    "close": 0.01082,
    "volume": 470301
  },
  {
    "time": 1768778100000,
    "open": 0.0108,
    "high": 0.01089,
    "low": 0.01075,
    "close": 0.01077,
    "volume": 347249
  },
  {
    "time": 1768779000000,
    "open": 0.01078,
    "high": 0.01082,
    "low": 0.00829,
    "close": 0.01024,
    "volume": 1482116
  },
  {
    "time": 1768779900000,
    "open": 0.01029,
    "high": 0.01031,
    "low": 0.00939,
    "close": 0.00948,
    "volume": 689161
  },
  {
    "time": 1768780800000,
    "open": 0.00948,
    "high": 0.00959,
    "low": 0.00814,
    "close": 0.00939,
    "volume": 1366602
  },
  {
    "time": 1768781700000,
    "open": 0.00938,
    "high": 0.00948,
    "low": 0.00889,
    "close": 0.00904,
    "volume": 483389
  },
  {
    "time": 1768782600000,
    "open": 0.00901,
    "high": 0.00924,
    "low": 0.00821,
    "close": 0.0083,
    "volume": 827504
  },
  {
    "time": 1768783500000,
    "open": 0.00836,
    "high": 0.01026,
    "low": 0.00811,
    "close": 0.00932,
    "volume": 1074947
  },
  {
    "time": 1768784400000,
    "open": 0.00932,
    "high": 0.01032,
    "low": 0.00888,
    "close": 0.0096,
    "volume": 908260
  },
  {
    "time": 1768785300000,
    "open": 0.0096,
    "high": 0.00992,
    "low": 0.00951,
    "close": 0.00979,
    "volume": 555043
  },
  {
    "time": 1768786200000,
    "open": 0.00978,
    "high": 0.00986,
    "low": 0.00955,
    "close": 0.00972,
    "volume": 427922
  },
  {
    "time": 1768787100000,
    "open": 0.00969,
    "high": 0.00973,
    "low": 0.00948,
    "close": 0.0095,
    "volume": 435511
  },
  {
    "time": 1768788000000,
    "open": 0.00948,
    "high": 0.00959,
    "low": 0.00941,
    "close": 0.00944,
    "volume": 456574
  },
  {
    "time": 1768788900000,
    "open": 0.00943,
    "high": 0.0095,
    "low": 0.00921,
    "close": 0.00931,
    "volume": 505591
  },
  {
    "time": 1768789800000,
    "open": 0.00932,
    "high": 0.00941,
    "low": 0.00921,
    "close": 0.00929,
    "volume": 464155
  },
  {
    "time": 1768790700000,
    "open": 0.00929,
    "high": 0.00937,
    "low": 0.00919,
    "close": 0.00923,
    "volume": 382944
  },
  {
    "time": 1768791600000,
    "open": 0.00923,
    "high": 0.0093,
    "low": 0.00892,
    "close": 0.00924,
    "volume": 404237
  },
  {
    "time": 1768792500000,
    "open": 0.00922,
    "high": 0.00928,
    "low": 0.00914,
    "close": 0.00923,
    "volume": 327923
  },
  {
    "time": 1768793400000,
    "open": 0.00922,
    "high": 0.00924,
    "low": 0.00916,
    "close": 0.0092,
    "volume": 297489
  },
  {
    "time": 1768794300000,
    "open": 0.00921,
    "high": 0.00923,
    "low": 0.00913,
    "close": 0.00917,
    "volume": 505246
  },
  {
    "time": 1768795200000,
    "open": 0.00918,
    "high": 0.00921,
    "low": 0.00901,
    "close": 0.00904,
    "volume": 353650
  },
  {
    "time": 1768796100000,
    "open": 0.00904,
    "high": 0.00912,
    "low": 0.00899,
    "close": 0.00909,
    "volume": 381038
  },
  {
    "time": 1768797000000,
    "open": 0.00909,
    "high": 0.00916,
    "low": 0.00901,
    "close": 0.00902,
    "volume": 351053
  },
  {
    "time": 1768797900000,
    "open": 0.00901,
    "high": 0.00911,
    "low": 0.00888,
    "close": 0.00895,
    "volume": 505587
  },
  {
    "time": 1768798800000,
    "open": 0.00892,
    "high": 0.00898,
    "low": 0.00877,
    "close": 0.0089,
    "volume": 434841
  },
  {
    "time": 1768799700000,
    "open": 0.0089,
    "high": 0.00896,
    "low": 0.00885,
    "close": 0.00892,
    "volume": 455489
  },
  {
    "time": 1768800600000,
    "open": 0.00891,
    "high": 0.00893,
    "low": 0.00883,
    "close": 0.00888,
    "volume": 407970
  },
  {
    "time": 1768801500000,
    "open": 0.00888,
    "high": 0.00891,
    "low": 0.00868,
    "close": 0.00871,
    "volume": 506217
  },
  {
    "time": 1768802400000,
    "open": 0.00871,
    "high": 0.00936,
    "low": 0.00862,
    "close": 0.00901,
    "volume": 742682
  },
  {
    "time": 1768803300000,
    "open": 0.00899,
    "high": 0.00901,
    "low": 0.00884,
    "close": 0.00886,
    "volume": 401053
  },
  {
    "time": 1768804200000,
    "open": 0.00885,
    "high": 0.00892,
    "low": 0.00876,
    "close": 0.00876,
    "volume": 414412
  },
  {
    "time": 1768805100000,
    "open": 0.00876,
    "high": 0.00878,
    "low": 0.00846,
    "close": 0.00847,
    "volume": 603410
  },
  {
    "time": 1768806000000,
    "open": 0.00848,
    "high": 0.00863,
    "low": 0.00846,
    "close": 0.00851,
    "volume": 372963
  },
  {
    "time": 1768806900000,
    "open": 0.00852,
    "high": 0.00866,
    "low": 0.00851,
    "close": 0.00865,
    "volume": 382430
  },
  {
    "time": 1768807800000,
    "open": 0.00863,
    "high": 0.00866,
    "low": 0.00858,
    "close": 0.00865,
    "volume": 334966
  },
  {
    "time": 1768808700000,
    "open": 0.00864,
    "high": 0.00864,
    "low": 0.00853,
    "close": 0.00858,
    "volume": 333496
  },
  {
    "time": 1768809600000,
    "open": 0.00859,
    "high": 0.00864,
    "low": 0.00854,
    "close": 0.00862,
    "volume": 442631
  },
  {
    "time": 1768810500000,
    "open": 0.00861,
    "high": 0.00864,
    "low": 0.00854,
    "close": 0.00856,
    "volume": 423571
  },
  {
    "time": 1768811400000,
    "open": 0.00855,
    "high": 0.00857,
    "low": 0.00836,
    "close": 0.00846,
    "volume": 361157
  },
  {
    "time": 1768812300000,
    "open": 0.00846,
    "high": 0.0085,
    "low": 0.00834,
    "close": 0.00836,
    "volume": 319168
  },
  {
    "time": 1768813200000,
    "open": 0.00836,
    "high": 0.00839,
    "low": 0.00806,
    "close": 0.00807,
    "volume": 484346
  },
  {
    "time": 1768814100000,
    "open": 0.0081,
    "high": 0.00834,
    "low": 0.00807,
    "close": 0.00832,
    "volume": 451892
  },
  {
    "time": 1768815000000,
    "open": 0.00831,
    "high": 0.00836,
    "low": 0.00825,
    "close": 0.0083,
    "volume": 304068
  },
  {
    "time": 1768815900000,
    "open": 0.0083,
    "high": 0.00833,
    "low": 0.00821,
    "close": 0.00822,
    "volume": 348221
  },
  {
    "time": 1768816800000,
    "open": 0.00824,
    "high": 0.00832,
    "low": 0.00815,
    "close": 0.00824,
    "volume": 426662
  },
  {
    "time": 1768817700000,
    "open": 0.00824,
    "high": 0.00838,
    "low": 0.00823,
    "close": 0.00827,
    "volume": 288890
  },
  {
    "time": 1768818600000,
    "open": 0.00827,
    "high": 0.00832,
    "low": 0.0082,
    "close": 0.00829,
    "volume": 263141
  },
  {
    "time": 1768819500000,
    "open": 0.00829,
    "high": 0.00835,
    "low": 0.0082,
    "close": 0.0082,
    "volume": 377071
  },
  {
    "time": 1768820400000,
    "open": 0.0082,
    "high": 0.00833,
    "low": 0.00817,
    "close": 0.00832,
    "volume": 436456
  },
  {
    "time": 1768821300000,
    "open": 0.00832,
    "high": 0.00833,
    "low": 0.00824,
    "close": 0.00828,
    "volume": 291621
  },
  {
    "time": 1768822200000,
    "open": 0.00828,
    "high": 0.00833,
    "low": 0.00818,
    "close": 0.00828,
    "volume": 419022
  },
  {
    "time": 1768823100000,
    "open": 0.0083,
    "high": 0.00833,
    "low": 0.0082,
    "close": 0.00821,
    "volume": 362729
  },
  {
    "time": 1768824000000,
    "open": 0.00821,
    "high": 0.00826,
    "low": 0.00812,
    "close": 0.00824,
    "volume": 315672
  },
  {
    "time": 1768824900000,
    "open": 0.00824,
    "high": 0.00825,
    "low": 0.00799,
    "close": 0.0081,
    "volume": 590451
  },
  {
    "time": 1768825800000,
    "open": 0.0081,
    "high": 0.00821,
    "low": 0.00807,
    "close": 0.00809,
    "volume": 411975
  },
  {
    "time": 1768826700000,
    "open": 0.00808,
    "high": 0.00841,
    "low": 0.00802,
    "close": 0.00835,
    "volume": 483694
  },
  {
    "time": 1768827600000,
    "open": 0.00834,
    "high": 0.0088,
    "low": 0.00821,
    "close": 0.00828,
    "volume": 580239
  },
  {
    "time": 1768828500000,
    "open": 0.00828,
    "high": 0.00834,
    "low": 0.00821,
    "close": 0.00833,
    "volume": 390225
  },
  {
    "time": 1768829400000,
    "open": 0.00831,
    "high": 0.00835,
    "low": 0.00761,
    "close": 0.00773,
    "volume": 649606
  },
  {
    "time": 1768830300000,
    "open": 0.00775,
    "high": 0.00792,
    "low": 0.00775,
    "close": 0.00781,
    "volume": 572780
  },
  {
    "time": 1768831200000,
    "open": 0.00781,
    "high": 0.00802,
    "low": 0.00778,
    "close": 0.00792,
    "volume": 553305
  },
  {
    "time": 1768832100000,
    "open": 0.00792,
    "high": 0.00803,
    "low": 0.00772,
    "close": 0.00776,
    "volume": 618778
  },
  {
    "time": 1768833000000,
    "open": 0.00775,
    "high": 0.00781,
    "low": 0.00764,
    "close": 0.00775,
    "volume": 375720
  },
  {
    "time": 1768833900000,
    "open": 0.00774,
    "high": 0.00784,
    "low": 0.00763,
    "close": 0.00763,
    "volume": 351283
  },
  {
    "time": 1768834800000,
    "open": 0.00767,
    "high": 0.00775,
    "low": 0.00767,
    "close": 0.00775,
    "volume": 372323
  },
  {
    "time": 1768835700000,
    "open": 0.00777,
    "high": 0.00799,
    "low": 0.00777,
    "close": 0.00796,
    "volume": 606101
  },
  {
    "time": 1768836600000,
    "open": 0.00794,
    "high": 0.00808,
    "low": 0.00793,
    "close": 0.00804,
    "volume": 453388
  },
  {
    "time": 1768837500000,
    "open": 0.00805,
    "high": 0.00946,
    "low": 0.00802,
    "close": 0.00891,
    "volume": 1437877
  },
  {
    "time": 1768838400000,
    "open": 0.00889,
    "high": 0.00994,
    "low": 0.00879,
    "close": 0.00939,
    "volume": 1338459
  },
  {
    "time": 1768839300000,
    "open": 0.00939,
    "high": 0.00984,
    "low": 0.00916,
    "close": 0.00918,
    "volume": 819646
  },
  {
    "time": 1768840200000,
    "open": 0.00916,
    "high": 0.00959,
    "low": 0.00872,
    "close": 0.0092,
    "volume": 868976
  },
  {
    "time": 1768841100000,
    "open": 0.00918,
    "high": 0.01096,
    "low": 0.00918,
    "close": 0.01074,
    "volume": 1117076
  },
  {
    "time": 1768842000000,
    "open": 0.01075,
    "high": 0.01118,
    "low": 0.01047,
    "close": 0.01072,
    "volume": 427374
  }
]